CHANGELOG.md
countdown_sleep/__init__.py
countdown_sleep/main.py
countdown_sleep-0.1.1.dist-info/entry_points.txt
countdown_sleep-0.1.1.dist-info/LICENSE.txt
countdown_sleep-0.1.1.dist-info/WHEEL
countdown_sleep-0.1.1.dist-info/METADATA
countdown_sleep-0.1.1.dist-info/RECORD
